jetnet/__init__.py
jetnet/datasets/__init__.py
jetnet/datasets/dataset.py
jetnet/datasets/jetnet.py
jetnet/datasets/normalisations.py
jetnet/datasets/qgjets.py
jetnet/datasets/toptagging.py
jetnet/datasets/utils.py
jetnet/evaluation/__init__.py
jetnet/evaluation/gen_metrics.py
jetnet/evaluation/particlenet.py
jetnet/evaluation/fpnd_resources/__init__.py
jetnet/evaluation/fpnd_resources/jetnet/__init__.py
jetnet/evaluation/fpnd_resources/jetnet/30_particles/__init__.py
jetnet/evaluation/fpnd_resources/jetnet/30_particles/g_mu.txt
jetnet/evaluation/fpnd_resources/jetnet/30_particles/g_sigma.txt
jetnet/evaluation/fpnd_resources/jetnet/30_particles/pnet_state_dict.pt
jetnet/evaluation/fpnd_resources/jetnet/30_particles/q_mu.txt
jetnet/evaluation/fpnd_resources/jetnet/30_particles/q_sigma.txt
jetnet/evaluation/fpnd_resources/jetnet/30_particles/t_mu.txt
jetnet/evaluation/fpnd_resources/jetnet/30_particles/t_sigma.txt
jetnet/losses/__init__.py
jetnet/losses/losses.py
jetnet/utils/__init__.py
jetnet/utils/coord_transform.py
jetnet/utils/utils.py
jetnet-0.2.5.dist-info/LICENSE
jetnet-0.2.5.dist-info/METADATA
jetnet-0.2.5.dist-info/WHEEL
jetnet-0.2.5.dist-info/top_level.txt
jetnet-0.2.5.dist-info/RECORD
