Metadata-Version: 2.1
Name: jetnet
Version: 0.2.5
Summary: Jets + ML integration
Home-page: http://github.com/jet-net/JetNet
Author: Raghav Kansal
Author-email: rkansal@cern.ch
License: MIT
Classifier: Development Status :: 3 - Alpha
Classifier: License :: OSI Approved :: MIT License
Classifier: Programming Language :: Python :: 3
Classifier: Programming Language :: Python :: 3.7
Classifier: Programming Language :: Python :: 3.8
Classifier: Programming Language :: Python :: 3.9
Classifier: Programming Language :: Python :: 3.10
Classifier: Programming Language :: Python :: 3.11
Requires-Python: >=3.7
License-File: LICENSE
Requires-Dist: numpy>=1.21.0
Requires-Dist: torch>=1.8.0
Requires-Dist: energyflow>=1.3.0
Requires-Dist: scipy>=1.6.2
Requires-Dist: awkward>=1.4.0
Requires-Dist: coffea>=0.7.0
Requires-Dist: h5py>=3.0.0
Requires-Dist: pandas
Requires-Dist: tables
Requires-Dist: requests
Requires-Dist: tqdm
Provides-Extra: emdloss
Requires-Dist: qpth; extra == "emdloss"
Requires-Dist: cvxpy; extra == "emdloss"
